Metadata-Version: 2.1
Name: crawford-turing-calculator-project
Version: 0.1
Summary: Simple Calculator with Memory
Author: Christina Crawford
Author-email: christinalcrawford@gmail.com
License: MIT License
